xldparser/__init__.py
xldparser/constants.py
xldparser/second_sector.py
xldparser/toc_entry.py
xldparser/track.py
xldparser-0.1.4.dist-info/METADATA
xldparser-0.1.4.dist-info/WHEEL
xldparser-0.1.4.dist-info/licenses/LICENSE
xldparser-0.1.4.dist-info/RECORD
