Metadata-Version: 2.4
Name: xldparser
Version: 0.1.4
Summary: Parse the X Lossless Decoder a.k.a. XLD app log files
Project-URL: Homepage, https://github.com/rinsuki/python-xldparser
Project-URL: Repository, https://github.com/rinsuki/python-xldparser.git
Project-URL: Issues, https://github.com/rinsuki/python-xldparser/issues
Project-URL: Changelog, https://github.com/rinsuki/python-xldparser/releases
Author-email: rinsuki <428rinsuki+pypi@gmail.com>
License-Expression: MIT
License-File: LICENSE
Classifier: Development Status :: 4 - Beta
Classifier: Intended Audience :: Developers
Classifier: License :: OSI Approved :: MIT License
Requires-Python: >=3.12.6
